Workbook
Name Slicer_product_id: #N/A

Sheet Customers
A1: customer_id | B1: name | C1: age | D1: gender | E1: city | F1: region | G1: signup_date | H1: Column1
A2: ="C"&TEXT(ROW()-1,"0000") -> C0001 | B2: Sonali Singh | C2: =RANDBETWEEN(18,65) -> 26 | D2: Other | E2: Bangalore | F2: South | G2: 45673
A3: ="C"&TEXT(ROW()-1,"0000") -> C0002 | B3: Mishruuuuu | C3: =RANDBETWEEN(18,65) -> 23 | D3: Female | E3: Pune | F3: West | G3: 45675
A4: ="C"&TEXT(ROW()-1,"0000") -> C0003 | B4: Manvi Singh | C4: =RANDBETWEEN(18,65) -> 18 | D4: Female | E4: Pune | F4: West | G4: 45672
A5: ="C"&TEXT(ROW()-1,"0000") -> C0004 | B5: Ashish Singh Parmar | C5: =RANDBETWEEN(18,65) -> 46 | D5: Female | E5: Bangalore | F5: East | G5: 45670
A6: ="C"&TEXT(ROW()-1,"0000") -> C0005 | B6: Priya Singh | C6: =RANDBETWEEN(18,65) -> 21 | D6: Female | E6: Delhi | F6: North | G6: 45668
A7: ="C"&TEXT(ROW()-1,"0000") -> C0006 | B7: Rahul Sharma | C7: =RANDBETWEEN(18,65) -> 44 | D7: Male | E7: Kolkata | F7: East | G7: 45667
A8: ="C"&TEXT(ROW()-1,"0000") -> C0007 | B8: Tanya Kumari | C8: =RANDBETWEEN(18,65) -> 19 | D8: Other | E8: Delhi | F8: South | G8: 45669
A9: ="C"&TEXT(ROW()-1,"0000") -> C0008 | B9: Krish Kumar | C9: =RANDBETWEEN(18,65) -> 56 | D9: Female | E9: Pune | F9: East | G9: 45674
A10: ="C"&TEXT(ROW()-1,"0000") -> C0009 | B10: Ajit Prasad | C10: =RANDBETWEEN(18,65) -> 50 | D10: Male | E10: Kolkata | F10: East | G10: 45671
A11: ="C"&TEXT(ROW()-1,"0000") -> C0010 | B11: Ajit Prasad | C11: =RANDBETWEEN(18,65) -> 29 | D11: Male | E11: Kolkata | F11: East | G11: 45671
A12: ="C"&TEXT(ROW()-1,"0000") -> C0011 | E12: =COUNTIF(E2:E11,"Kolkata") -> 3 | H12: =IF(C12<30,"Young Adult","Older") -> Young Adult
A13: ="C"&TEXT(ROW()-1,"0000") -> C0012 | B13: =COUNTA(B2:B11) -> 10 | C13: =COUNT(C2:C11) -> 10 | G13: =YEAR(G2) -> 2025 | H13: =IF(C13<30,"Young Adult","Older") -> Young Adult
A14: ="C"&TEXT(ROW()-1,"0000") -> C0013 | H14: =IF(C14<30,"Young Adult","Older") -> Young Adult
A15: ="C"&TEXT(ROW()-1,"0000") -> C0014 | B15: =LEN(B2) -> 12 | E15: Kolkata | G15: =MONTH(G2) -> 1 | H15: =IF(C15<30,"Young Adult","Older") -> Young Adult
A16: ="C"&TEXT(ROW()-1,"0000") -> C0015 | B16: =LEFT(A2,1) -> C | E16: =TRIM(" Kolkata ") -> Kolkata | G16: =DAY(G2) -> 16 | H16: =IF(C16<30,"Young Adult","Older") -> Young Adult
A17: ="C"&TEXT(ROW()-1,"0000") -> C0016 | E17: =TRIM(E2) -> Bangalore | G17: =TODAY() -> 46306 | H17: =IF(C17<30,"Young Adult","Older") -> Young Adult
A18: ="C"&TEXT(ROW()-1,"0000") -> C0017 | B18: =RIGHT(A2,4) -> 0001 | G18: =EOMONTH(G2,0) -> 45688 | H18: =IF(C18<30,"Young Adult","Older") -> Young Adult
A19: ="C"&TEXT(ROW()-1,"0000") -> C0018 | B19: =MID(A2,2,4) -> 0001 | E19: =SUBSTITUTE(E2,"Bangalore","Calcutta") -> Calcutta | G19: =EOMONTH(G2,1) -> 45716 | H19: =IF(C19<30,"Young Adult","Older") -> Young Adult
A20: ="C"&TEXT(ROW()-1,"0000") -> C0019 | E20: =_xlfn.CONCAT(B2," - ",E2) -> Sonali Singh - Bangalore | H20: =IF(C20<30,"Young Adult","Older") -> Young Adult
A21: ="C"&TEXT(ROW()-1,"0000") -> C0020 | H21: =IF(C21<30,"Young Adult","Older") -> Young Adult
A22: ="C"&TEXT(ROW()-1,"0000") -> C0021 | H22: =IF(C22<30,"Young Adult","Older") -> Young Adult
A23: ="C"&TEXT(ROW()-1,"0000") -> C0022 | H23: =IF(C23<30,"Young Adult","Older") -> Young Adult
A24: ="C"&TEXT(ROW()-1,"0000") -> C0023 | H24: =IF(C24<30,"Young Adult","Older") -> Young Adult
A25: ="C"&TEXT(ROW()-1,"0000") -> C0024 | H25: =IF(C25<30,"Young Adult","Older") -> Young Adult
A26: ="C"&TEXT(ROW()-1,"0000") -> C0025 | H26: =IF(C26<30,"Young Adult","Older") -> Young Adult
A27: ="C"&TEXT(ROW()-1,"0000") -> C0026 | H27: =IF(C27<30,"Young Adult","Older") -> Young Adult
A28: ="C"&TEXT(ROW()-1,"0000") -> C0027 | H28: =IF(C28<30,"Young Adult","Older") -> Young Adult
A29: ="C"&TEXT(ROW()-1,"0000") -> C0028 | H29: =IF(C29<30,"Young Adult","Older") -> Young Adult
A30: ="C"&TEXT(ROW()-1,"0000") -> C0029 | H30: =IF(C30<30,"Young Adult","Older") -> Young Adult
A31: ="C"&TEXT(ROW()-1,"0000") -> C0030 | H31: =IF(C31<30,"Young Adult","Older") -> Young Adult
A32: ="C"&TEXT(ROW()-1,"0000") -> C0031 | H32: =IF(C32<30,"Young Adult","Older") -> Young Adult
... A1001: ="C"&TEXT(ROW()-1,"0000") -> C1000 | H1001: =IF(C1001<30,"Young Adult","Older") -> Young Adult

Sheet Products
